[{"Average response time": "7124", "Min response time": "5417", "# requests": "4", "Method": "GET", "# failures": "0", "Requests/s": "0.14", "Name": "silver-0", "Max response time": "8194", "Median response time": "7400", "Average Content Size": "19"}, {"Average response time": "7698", "Min response time": "6597", "# requests": "3", "Method": "GET", "# failures": "0", "Requests/s": "0.11", "Name": "silver-1", "Max response time": "8596", "Median response time": "7900", "Average Content Size": "19"}, {"Average response time": "7370", "Min response time": "5417", "# requests": "7", "Method": "None", "# failures": "0", "Requests/s": "0.25", "Name": "Total", "Max response time": "8596", "Median response time": "7500", "Average Content Size": "19"}]