[{"Name": "gold-0", "# failures": "0", "# requests": "39", "Min response time": "416", "Average response time": "1483", "Method": "GET", "Max response time": "3294", "Average Content Size": "19", "Requests/s": "0.66", "Median response time": "1300"}, {"Name": "gold-1", "# failures": "0", "# requests": "41", "Min response time": "362", "Average response time": "1450", "Method": "GET", "Max response time": "3251", "Average Content Size": "19", "Requests/s": "0.70", "Median response time": "1500"}, {"Name": "gold-2", "# failures": "0", "# requests": "41", "Min response time": "411", "Average response time": "1398", "Method": "GET", "Max response time": "3140", "Average Content Size": "19", "Requests/s": "0.70", "Median response time": "1300"}, {"Name": "gold-3", "# failures": "0", "# requests": "41", "Min response time": "627", "Average response time": "1396", "Method": "GET", "Max response time": "2594", "Average Content Size": "19", "Requests/s": "0.70", "Median response time": "1300"}, {"Name": "gold-4", "# failures": "0", "# requests": "46", "Min response time": "454", "Average response time": "1296", "Method": "GET", "Max response time": "2542", "Average Content Size": "19", "Requests/s": "0.78", "Median response time": "1200"}, {"Name": "gold-5", "# failures": "0", "# requests": "40", "Min response time": "610", "Average response time": "1480", "Method": "GET", "Max response time": "2745", "Average Content Size": "19", "Requests/s": "0.68", "Median response time": "1400"}, {"Name": "Total", "# failures": "0", "# requests": "248", "Min response time": "362", "Average response time": "1414", "Method": "None", "Max response time": "3294", "Average Content Size": "19", "Requests/s": "4.22", "Median response time": "1300"}]