[{"bench":{"namespaces":[{"name":"gold","chart":{"Name":"my-app","DirPath":"/chart/exp2app"},"config":{"Settings":[{"Parameter":{"Name":"demoCPU","Resource":"","Searchspace":{"Min":800,"Max":800,"Granularity":100},"Prefix":"","Suffix":"m"},"Value":{"Value":800,"Type":"int"}},{"Parameter":{"Name":"worker1CPU","Resource":"","Searchspace":{"Min":2200,"Max":2200,"Granularity":1},"Prefix":"","Suffix":"m"},"Value":{"Value":2200,"Type":"int"}},{"Parameter":{"Name":"worker1Replicas","Resource":"","Searchspace":{"Min":0,"Max":0,"Granularity":1},"Prefix":"","Suffix":""},"Value":{"Value":0,"Type":"int"}},{"Parameter":{"Name":"worker2CPU","Resource":"","Searchspace":{"Min":750,"Max":750,"Granularity":1},"Prefix":"","Suffix":"m"},"Value":{"Value":750,"Type":"int"}},{"Parameter":{"Name":"worker2Replicas","Resource":"","Searchspace":{"Min":1,"Max":1,"Granularity":1},"Prefix":"","Suffix":""},"Value":{"Value":1,"Type":"int"}},{"Parameter":{"Name":"worker3CPU","Resource":"","Searchspace":{"Min":250,"Max":250,"Granularity":1},"Prefix":"","Suffix":"m"},"Value":{"Value":250,"Type":"int"}},{"Parameter":{"Name":"worker3Replicas","Resource":"","Searchspace":{"Min":2,"Max":2,"Granularity":1},"Prefix":"","Suffix":""},"Value":{"Value":2,"Type":"int"}}]}}],"experiment":{"Iteration":0,"Sample":0,"Locustconfig":{"Name":"","ScriptPath":"/tmp/locustwrap/locust_exp.py","Users":8,"HatchRate":8,"DurationInSeconds":60,"WarmupInSeconds":30,"Host":""},"OutputDir":"Results/exp3/gold/8_tenants-ex1/op/","Type":"LocustBatchExperiment","Failed":false}},"result":{"Results":{"name":"","Distribution":[{"Name":"GET gold-0","# requests":"32","50%":"1800","66%":"2000","75%":"2100","80%":"2200","90%":"2600","95%":"2700","98%":"3500","99%":"3500","100%":"3500"},{"Name":"GET gold-1","# requests":"34","50%":"1700","66%":"2000","75%":"2100","80%":"2100","90%":"2200","95%":"2600","98%":"2600","99%":"2600","100%":"2600"},{"Name":"GET gold-2","# requests":"32","50%":"1700","66%":"2000","75%":"2200","80%":"2300","90%":"2500","95%":"3200","98%":"3400","99%":"3400","100%":"3400"},{"Name":"GET gold-3","# requests":"34","50%":"1600","66%":"1900","75%":"2000","80%":"2000","90%":"2300","95%":"2600","98%":"3000","99%":"3000","100%":"3000"},{"Name":"GET gold-4","# requests":"32","50%":"1800","66%":"2000","75%":"2100","80%":"2100","90%":"2400","95%":"2700","98%":"2800","99%":"2800","100%":"2800"},{"Name":"GET gold-5","# requests":"30","50%":"1900","66%":"2000","75%":"2200","80%":"2600","90%":"2800","95%":"2900","98%":"3300","99%":"3300","100%":"3300"},{"Name":"GET gold-6","# requests":"32","50%":"1800","66%":"2000","75%":"2100","80%":"2300","90%":"2500","95%":"2900","98%":"3500","99%":"3500","100%":"3500"},{"Name":"GET gold-7","# requests":"31","50%":"1800","66%":"1900","75%":"2000","80%":"2000","90%":"2600","95%":"2700","98%":"2900","99%":"2900","100%":"2900"},{"Name":"Total","# requests":"257","50%":"1800","66%":"2000","75%":"2100","80%":"2200","90%":"2600","95%":"2800","98%":"3000","99%":"3400","100%":"3500"}],"Requests":[{"Name":"gold-0","# failures":"0","Max response time":"3452","Median response time":"1800","Average response time":"1850","Min response time":"817","Method":"GET","Requests/s":"0.54","# requests":"32","Average Content Size":"19"},{"Name":"gold-1","# failures":"0","Max response time":"2596","Median response time":"1700","Average response time":"1707","Min response time":"703","Method":"GET","Requests/s":"0.57","# requests":"34","Average Content Size":"19"},{"Name":"gold-2","# failures":"0","Max response time":"3407","Median response time":"1700","Average response time":"1833","Min response time":"803","Method":"GET","Requests/s":"0.54","# requests":"32","Average Content Size":"19"},{"Name":"gold-3","# failures":"0","Max response time":"2992","Median response time":"1600","Average response time":"1739","Min response time":"830","Method":"GET","Requests/s":"0.57","# requests":"34","Average Content Size":"19"},{"Name":"gold-4","# failures":"0","Max response time":"2781","Median response time":"1800","Average response time":"1846","Min response time":"947","Method":"GET","Requests/s":"0.54","# requests":"32","Average Content Size":"19"},{"Name":"gold-5","# failures":"0","Max response time":"3274","Median response time":"1900","Average response time":"1941","Min response time":"1102","Method":"GET","Requests/s":"0.51","# requests":"30","Average Content Size":"19"},{"Name":"gold-6","# failures":"0","Max response time":"3541","Median response time":"1800","Average response time":"1814","Min response time":"658","Method":"GET","Requests/s":"0.54","# requests":"32","Average Content Size":"19"},{"Name":"gold-7","# failures":"0","Max response time":"2853","Median response time":"1800","Average response time":"1856","Min response time":"1067","Method":"GET","Requests/s":"0.52","# requests":"31","Average Content Size":"19"},{"Name":"Total","# failures":"0","Max response time":"3541","Median response time":"1800","Average response time":"1821","Min response time":"658","Method":"None","Requests/s":"4.34","# requests":"257","Average Content Size":"19"}],"Duration":60732913075},"DistTotal":{"Name":"","# requests":"0","50%":"0","66%":"0","75%":"0","80%":"0","90%":"0","95%":"0","98%":"0","99%":"0","100%":"0"},"ReqTotal":{"Name":"","# failures":"0","Max response time":"0","Median response time":"0","Average response time":"0","Min response time":"0","Method":"","Requests/s":"0","# requests":"0","Average Content Size":"0"},"Type":"LocustBatchExperimentResult","Failed":false}}]